azumio_foodai/__init__.py
azumio_foodai/food_response.py
azumio_foodai/foodai.py
azumio_foodai-1.0.4.dist-info/METADATA
azumio_foodai-1.0.4.dist-info/WHEEL
azumio_foodai-1.0.4.dist-info/top_level.txt
azumio_foodai-1.0.4.dist-info/RECORD
