Metadata-Version: 2.1
Name: azumio_foodai
Version: 1.0.4
Home-page: https://github.com/azumio/foodai-clients/tree/master/foodai
Author: Igor Rendulic
Author-email: Igor Rendulic <igor@azumio.com>
Project-URL: Homepage, https://github.com/azumio/foodai-clients/tree/master/foodai
Project-URL: Bug Tracker, https://github.com/azumio/foodai-clients/issues
Classifier: Programming Language :: Python :: 3
Classifier: License :: OSI Approved :: Apache Software License
Classifier: Operating System :: OS Independent
Classifier: Topic :: Scientific/Engineering :: Artificial Intelligence
Classifier: Intended Audience :: Developers
Classifier: Natural Language :: English
Requires-Python: >=3.7
Requires-Dist: requests
Requires-Dist: pillow
Requires-Dist: dacite
